{"frames": {

"bullet.png":
{
	"frame": {"x":776,"y":226,"w":3,"h":10},
	"rotated": false,
	"trimmed": false,
	"spriteSourceSize": {"x":0,"y":0,"w":3,"h":10},
	"sourceSize": {"w":3,"h":10}
},
"enemy1.png":
{
	"frame": {"x":728,"y":226,"w":46,"h":46},
	"rotated": false,
	"trimmed": false,
	"spriteSourceSize": {"x":0,"y":0,"w":46,"h":46},
	"sourceSize": {"w":46,"h":46}
},
"enemy2.png":
{
	"frame": {"x":508,"y":226,"w":146,"h":130},
	"rotated": false,
	"trimmed": false,
	"spriteSourceSize": {"x":0,"y":0,"w":146,"h":130},
	"sourceSize": {"w":146,"h":130}
},
"enemy3.png":
{
	"frame": {"x":508,"y":2,"w":278,"h":222},
	"rotated": false,
	"trimmed": false,
	"spriteSourceSize": {"x":0,"y":0,"w":278,"h":222},
	"sourceSize": {"w":278,"h":222}
},
"explosion.png":
{
	"frame": {"x":2,"y":2,"w":504,"h":504},
	"rotated": false,
	"trimmed": true,
	"spriteSourceSize": {"x":4,"y":4,"w":504,"h":504},
	"sourceSize": {"w":512,"h":512}
},
"fighter.png":
{
	"frame": {"x":656,"y":226,"w":70,"h":86},
	"rotated": false,
	"trimmed": false,
	"spriteSourceSize": {"x":0,"y":0,"w":70,"h":86},
	"sourceSize": {"w":70,"h":86}
},
"particle.png":
{
	"frame": {"x":781,"y":226,"w":3,"h":3},
	"rotated": false,
	"trimmed": false,
	"spriteSourceSize": {"x":0,"y":0,"w":3,"h":3},
	"sourceSize": {"w":3,"h":3}
},
"star.png":
{
	"frame": {"x":728,"y":274,"w":18,"h":20},
	"rotated": false,
	"trimmed": false,
	"spriteSourceSize": {"x":0,"y":0,"w":18,"h":20},
	"sourceSize": {"w":18,"h":20}
}},
"meta": {
	"app": "http://www.codeandweb.com/texturepacker",
	"version": "1.0",
	"image": "images.png",
	"format": "RGBA8888",
	"size": {"w":788,"h":508},
	"scale": "1",
	"smartupdate": "$TexturePacker:SmartUpdate:917d49dbd0deeab4a6f7cd5cb112401c:584b45569667560ed5e46c403d9a0dc8:9be8c185d95a5be4a06ec0067a3d8380$"
}
}
